setup.py
coinbits/__init__.py
coinbits/client.py
coinbits/encoding.py
coinbits.egg-info/PKG-INFO
coinbits.egg-info/SOURCES.txt
coinbits.egg-info/dependency_links.txt
coinbits.egg-info/requires.txt
coinbits.egg-info/top_level.txt
coinbits/protocol/__init__.py
coinbits/protocol/buffer.py
coinbits/protocol/exceptions.py
coinbits/protocol/fields.py
coinbits/protocol/serializers.py
coinbits/protocol/utils.py
coinbits/tests/__init__.py
coinbits/tests/test_encoding.py
coinbits/txns/__init__.py
coinbits/txns/exceptions.py
coinbits/txns/keys.py
coinbits/txns/scripts.py
coinbits/txns/wallet.py
coinbits/txns/tests/__init__.py
coinbits/txns/tests/test_keys.py