Metadata-Version: 1.1
Name: coinbits
Version: 0.3
Summary: A Python library for bitcoin peer to peer communication
Home-page: http://github.com/8468/coinbits
Author: Brian Muller
Author-email: bamuller@gmail.com
License: MIT
Platform: UNKNOWN
Requires: ecdsa
